kivy_deps/__init__.py
kivy_deps/sdl2/__init__.py
kivy_deps.sdl2-0.5.0.data/data/share/sdl2/bin/LICENSE.freetype.txt
kivy_deps.sdl2-0.5.0.data/data/share/sdl2/bin/LICENSE.harfbuzz.txt
kivy_deps.sdl2-0.5.0.data/data/share/sdl2/bin/LICENSE.zlib.txt
kivy_deps.sdl2-0.5.0.data/data/share/sdl2/bin/SDL2.dll
kivy_deps.sdl2-0.5.0.data/data/share/sdl2/bin/SDL2_image.dll
kivy_deps.sdl2-0.5.0.data/data/share/sdl2/bin/SDL2_mixer.dll
kivy_deps.sdl2-0.5.0.data/data/share/sdl2/bin/SDL2_ttf.dll
kivy_deps.sdl2-0.5.0.data/data/share/sdl2/bin/optional/LICENSE.modplug.txt
kivy_deps.sdl2-0.5.0.data/data/share/sdl2/bin/optional/LICENSE.ogg-vorbis.txt
kivy_deps.sdl2-0.5.0.data/data/share/sdl2/bin/optional/LICENSE.opus.txt
kivy_deps.sdl2-0.5.0.data/data/share/sdl2/bin/optional/LICENSE.opusfile.txt
kivy_deps.sdl2-0.5.0.data/data/share/sdl2/bin/optional/LICENSE.tiff.txt
kivy_deps.sdl2-0.5.0.data/data/share/sdl2/bin/optional/LICENSE.webp.txt
kivy_deps.sdl2-0.5.0.data/data/share/sdl2/bin/optional/libmodplug-1.dll
kivy_deps.sdl2-0.5.0.data/data/share/sdl2/bin/optional/libogg-0.dll
kivy_deps.sdl2-0.5.0.data/data/share/sdl2/bin/optional/libopus-0.dll
kivy_deps.sdl2-0.5.0.data/data/share/sdl2/bin/optional/libopusfile-0.dll
kivy_deps.sdl2-0.5.0.data/data/share/sdl2/bin/optional/libtiff-5.dll
kivy_deps.sdl2-0.5.0.data/data/share/sdl2/bin/optional/libwebp-7.dll
kivy_deps.sdl2-0.5.0.dist-info/METADATA
kivy_deps.sdl2-0.5.0.dist-info/WHEEL
kivy_deps.sdl2-0.5.0.dist-info/top_level.txt
kivy_deps.sdl2-0.5.0.dist-info/RECORD
