Metadata-Version: 2.1
Name: kivy-deps.sdl2
Version: 0.5.0
Summary: Repackaged binary dependency of Kivy.
Home-page: http://kivy.org/
Author: Kivy Crew
Author-email: kivy-dev@googlegroups.com
License: zlib
